tempestwx/__init__.py
tempestwx/py.typed
tempestwx/settings.py
tempestwx/settings_loader.py
tempestwx/version.py
tempestwx/_auth/__init__.py
tempestwx/_auth/token.py
tempestwx/_client/__init__.py
tempestwx/_client/base.py
tempestwx/_client/client.py
tempestwx/_client/processor.py
tempestwx/_client/api/__init__.py
tempestwx/_client/api/tempest_home/better_forecast/__init__.py
tempestwx/_client/api/tempest_home/better_forecast/better_forecast.py
tempestwx/_client/api/tempest_home/observations/__init__.py
tempestwx/_client/api/tempest_home/observations/observations.py
tempestwx/_client/api/tempest_home/stations/__init__.py
tempestwx/_client/api/tempest_home/stations/stations.py
tempestwx/_client/api/tempest_home/stats/__init__.py
tempestwx/_client/api/tempest_home/stats/stats.py
tempestwx/_client/decorators/__init__.py
tempestwx/_client/decorators/error_handler.py
tempestwx/_client/decorators/request_handler.py
tempestwx/_http/__init__.py
tempestwx/_http/base.py
tempestwx/_http/client.py
tempestwx/_http/concrete.py
tempestwx/_http/error.py
tempestwx/_http/wrapper.py
tempestwx/_models/__init__.py
tempestwx/_models/_serializer.py
tempestwx/_models/better_forecast.py
tempestwx/_models/better_forecast_current_conditions.py
tempestwx/_models/better_forecast_daily_forecast.py
tempestwx/_models/better_forecast_forecast.py
tempestwx/_models/better_forecast_hourly_forecast.py
tempestwx/_models/better_forecast_units.py
tempestwx/_models/device.py
tempestwx/_models/device_meta.py
tempestwx/_models/device_observation.py
tempestwx/_models/device_observation_summary.py
tempestwx/_models/device_settings.py
tempestwx/_models/lightning_event.py
tempestwx/_models/obs_air.py
tempestwx/_models/obs_air_ext.py
tempestwx/_models/obs_sky.py
tempestwx/_models/obs_sky_ext.py
tempestwx/_models/obs_st.py
tempestwx/_models/obs_st_ext.py
tempestwx/_models/observation.py
tempestwx/_models/rapid_wind.py
tempestwx/_models/station.py
tempestwx/_models/station_item.py
tempestwx/_models/station_meta.py
tempestwx-0.0.4.dist-info/METADATA
tempestwx-0.0.4.dist-info/WHEEL
tempestwx-0.0.4.dist-info/licenses/LICENSE
tempestwx-0.0.4.dist-info/RECORD
