Metadata-Version: 2.4
Name: tempestwx
Version: 0.0.4
Summary: Tempest SDK for Python
Project-URL: repository, https://github.com/greylabel/tempestwx
Author-email: Grant Gaudet <grant@greylabel.net>
License: MIT
License-File: LICENSE
Keywords: api,tempest,weather
Classifier: Development Status :: 3 - Alpha
Classifier: Intended Audience :: Developers
Classifier: License :: OSI Approved :: MIT License
Classifier: Programming Language :: Python
Classifier: Programming Language :: Python :: 3
Classifier: Programming Language :: Python :: 3.11
Classifier: Programming Language :: Python :: 3.12
Classifier: Programming Language :: Python :: 3.13
Classifier: Topic :: Software Development :: Libraries
Classifier: Typing :: Typed
Requires-Python: >=3.11
Requires-Dist: httpx>=0.28.1
Requires-Dist: pydantic-settings>=2.11.0
Requires-Dist: pydantic>=2.12.3
Requires-Dist: python-dotenv>=1.1.1
